smsfactor/__init__.py
smsfactor/smsfactor.py
smsfactor/resources/__init__.py
smsfactor/resources/exceptions.py
smsfactor-0.0.5.dist-info/LICENSE
smsfactor-0.0.5.dist-info/METADATA
smsfactor-0.0.5.dist-info/WHEEL
smsfactor-0.0.5.dist-info/top_level.txt
smsfactor-0.0.5.dist-info/RECORD
